{
    "serial_device":[
        {
            "deviceName": "Entrance_XK3190_DS8",
            "isActive": 1,
            "deviceID": "A",
            "comPort": "COM3",
            "baudrate": 9600,
            "timeout": 1,
            "pollingInterval": 1
        },
        {
            "deviceName": "Exit_XK3190_DS8",
            "isActive": 1,
            "deviceID": "A",
            "comPort": "COM5",
            "baudrate": 9600,
            "timeout": 1,
            "pollingInterval": 1
        }
    ]
}